pyloniex/__init__.py
pyloniex/constants.py
pyloniex/errors.py
pyloniex/utils.py
pyloniex/api/__init__.py
pyloniex/api/private.py
pyloniex/api/public.py
pyloniex-0.0.8.dist-info/METADATA
pyloniex-0.0.8.dist-info/RECORD
pyloniex-0.0.8.dist-info/WHEEL
pyloniex-0.0.8.dist-info/top_level.txt
