Metadata-Version: 2.1
Name: pyloniex
Version: 0.0.8
Summary: Python bindings for the Poloniex API
Home-page: https://github.com/adamrothman/pyloniex
Author: Adam Rothman
Author-email: rothman.adam@gmail.com
License: UNKNOWN
Platform: UNKNOWN
Requires-Dist: cryptography
Requires-Dist: requests
Requires-Dist: tenacity
